ohdsi/cohort_generator/__init__.py
ohdsi/cohort_generator/main.py
cohort_generator-0.3.0.dist-info/METADATA
cohort_generator-0.3.0.dist-info/WHEEL
cohort_generator-0.3.0.dist-info/top_level.txt
cohort_generator-0.3.0.dist-info/RECORD
