Metadata-Version: 2.1
Name: cohort-generator
Version: 0.3.0
Summary: Python wrapper for the OHDSI R packages
Home-page: https://github.com/vantage6/python-ohdsi
Requires-Python: >=3.10
Requires-Dist: rpy2 ==3.5.12
Provides-Extra: dev
